<?xml version="1.0" encoding="UTF-8"?>
<!DOCTYPE mapper PUBLIC "-//mybatis.org//DTD Mapper 3.0//EN" "http://mybatis.org/dtd/mybatis-3-mapper.dtd">
<mapper namespace="com.woniu.dao.LoantimeMapper">
  <resultMap id="BaseResultMap" type="com.woniu.domain.Loantime">
    <!--
      WARNING - @mbggenerated
      This element is automatically generated by MyBatis Generator, do not modify.
      This element was generated on Mon Aug 19 19:11:51 CST 2019.
    -->
    <id column="loantimeid" jdbcType="INTEGER" property="loantimeid" />
    <result column="loantime" jdbcType="INTEGER" property="loantime" />
  </resultMap>
  <sql id="Example_Where_Clause">
    <!--
      WARNING - @mbggenerated
      This element is automatically generated by MyBatis Generator, do not modify.
      This element was generated on Mon Aug 19 19:11:51 CST 2019.
    -->
    <where>
      <foreach collection="oredCriteria" item="criteria" separator="or">
        <if test="criteria.valid">
          <trim prefix="(" prefixOverrides="and" suffix=")">
            <foreach collection="criteria.criteria" item="criterion">
              <choose>
                <when test="criterion.noValue">
                  and ${criterion.condition}
                </when>
                <when test="criterion.singleValue">
                  and ${criterion.condition} #{criterion.value}
                </when>
                <when test="criterion.betweenValue">
                  and ${criterion.condition} #{criterion.value} and #{criterion.secondValue}
                </when>
                <when test="criterion.listValue">
                  and ${criterion.condition}
                  <foreach close=")" collection="criterion.value" item="listItem" open="(" separator=",">
                    #{listItem}
                  </foreach>
                </when>
              </choose>
            </foreach>
          </trim>
        </if>
      </foreach>
    </where>
  </sql>
  <sql id="Update_By_Example_Where_Clause">
    <!--
      WARNING - @mbggenerated
      This element is automatically generated by MyBatis Generator, do not modify.
      This element was generated on Mon Aug 19 19:11:51 CST 2019.
    -->
    <where>
      <foreach collection="example.oredCriteria" item="criteria" separator="or">
        <if test="criteria.valid">
          <trim prefix="(" prefixOverrides="and" suffix=")">
            <foreach collection="criteria.criteria" item="criterion">
              <choose>
                <when test="criterion.noValue">
                  and ${criterion.condition}
                </when>
                <when test="criterion.singleValue">
                  and ${criterion.condition} #{criterion.value}
                </when>
                <when test="criterion.betweenValue">
                  and ${criterion.condition} #{criterion.value} and #{criterion.secondValue}
                </when>
                <when test="criterion.listValue">
                  and ${criterion.condition}
                  <foreach close=")" collection="criterion.value" item="listItem" open="(" separator=",">
                    #{listItem}
                  </foreach>
                </when>
              </choose>
            </foreach>
          </trim>
        </if>
      </foreach>
    </where>
  </sql>
  <sql id="Base_Column_List">
    <!--
      WARNING - @mbggenerated
      This element is automatically generated by MyBatis Generator, do not modify.
      This element was generated on Mon Aug 19 19:11:51 CST 2019.
    -->
    loantimeid, loantime
  </sql>
  <select id="selectByExample" parameterType="com.woniu.domain.LoantimeExample" resultMap="BaseResultMap">
    <!--
      WARNING - @mbggenerated
      This element is automatically generated by MyBatis Generator, do not modify.
      This element was generated on Mon Aug 19 19:11:51 CST 2019.
    -->
    select
    <if test="distinct">
      distinct
    </if>
    <include refid="Base_Column_List" />
    from loantime
    <if test="_parameter != null">
      <include refid="Example_Where_Clause" />
    </if>
    <if test="orderByClause != null">
      order by ${orderByClause}
    </if>
  </select>
  <select id="selectByPrimaryKey" parameterType="java.lang.Integer" resultMap="BaseResultMap">
    <!--
      WARNING - @mbggenerated
      This element is automatically generated by MyBatis Generator, do not modify.
      This element was generated on Mon Aug 19 19:11:51 CST 2019.
    -->
    select 
    <include refid="Base_Column_List" />
    from loantime
    where loantimeid = #{loantimeid,jdbcType=INTEGER}
  </select>
  <delete id="deleteByPrimaryKey" parameterType="java.lang.Integer">
    <!--
      WARNING - @mbggenerated
      This element is automatically generated by MyBatis Generator, do not modify.
      This element was generated on Mon Aug 19 19:11:51 CST 2019.
    -->
    delete from loantime
    where loantimeid = #{loantimeid,jdbcType=INTEGER}
  </delete>
  <delete id="deleteByExample" parameterType="com.woniu.domain.LoantimeExample">
    <!--
      WARNING - @mbggenerated
      This element is automatically generated by MyBatis Generator, do not modify.
      This element was generated on Mon Aug 19 19:11:51 CST 2019.
    -->
    delete from loantime
    <if test="_parameter != null">
      <include refid="Example_Where_Clause" />
    </if>
  </delete>
  <insert id="insert" parameterType="com.woniu.domain.Loantime">
    <!--
      WARNING - @mbggenerated
      This element is automatically generated by MyBatis Generator, do not modify.
      This element was generated on Mon Aug 19 19:11:51 CST 2019.
    -->
    insert into loantime (loantimeid, loantime)
    values (#{loantimeid,jdbcType=INTEGER}, #{loantime,jdbcType=INTEGER})
  </insert>
  <insert id="insertSelective" parameterType="com.woniu.domain.Loantime">
    <!--
      WARNING - @mbggenerated
      This element is automatically generated by MyBatis Generator, do not modify.
      This element was generated on Mon Aug 19 19:11:51 CST 2019.
    -->
    insert into loantime
    <trim prefix="(" suffix=")" suffixOverrides=",">
      <if test="loantimeid != null">
        loantimeid,
      </if>
      <if test="loantime != null">
        loantime,
      </if>
    </trim>
    <trim prefix="values (" suffix=")" suffixOverrides=",">
      <if test="loantimeid != null">
        #{loantimeid,jdbcType=INTEGER},
      </if>
      <if test="loantime != null">
        #{loantime,jdbcType=INTEGER},
      </if>
    </trim>
  </insert>
  <select id="countByExample" parameterType="com.woniu.domain.LoantimeExample" resultType="java.lang.Integer">
    <!--
      WARNING - @mbggenerated
      This element is automatically generated by MyBatis Generator, do not modify.
      This element was generated on Mon Aug 19 19:11:51 CST 2019.
    -->
    select count(*) from loantime
    <if test="_parameter != null">
      <include refid="Example_Where_Clause" />
    </if>
  </select>
  <update id="updateByExampleSelective" parameterType="map">
    <!--
      WARNING - @mbggenerated
      This element is automatically generated by MyBatis Generator, do not modify.
      This element was generated on Mon Aug 19 19:11:51 CST 2019.
    -->
    update loantime
    <set>
      <if test="record.loantimeid != null">
        loantimeid = #{record.loantimeid,jdbcType=INTEGER},
      </if>
      <if test="record.loantime != null">
        loantime = #{record.loantime,jdbcType=INTEGER},
      </if>
    </set>
    <if test="_parameter != null">
      <include refid="Update_By_Example_Where_Clause" />
    </if>
  </update>
  <update id="updateByExample" parameterType="map">
    <!--
      WARNING - @mbggenerated
      This element is automatically generated by MyBatis Generator, do not modify.
      This element was generated on Mon Aug 19 19:11:51 CST 2019.
    -->
    update loantime
    set loantimeid = #{record.loantimeid,jdbcType=INTEGER},
      loantime = #{record.loantime,jdbcType=INTEGER}
    <if test="_parameter != null">
      <include refid="Update_By_Example_Where_Clause" />
    </if>
  </update>
  <update id="updateByPrimaryKeySelective" parameterType="com.woniu.domain.Loantime">
    <!--
      WARNING - @mbggenerated
      This element is automatically generated by MyBatis Generator, do not modify.
      This element was generated on Mon Aug 19 19:11:51 CST 2019.
    -->
    update loantime
    <set>
      <if test="loantime != null">
        loantime = #{loantime,jdbcType=INTEGER},
      </if>
    </set>
    where loantimeid = #{loantimeid,jdbcType=INTEGER}
  </update>
  <update id="updateByPrimaryKey" parameterType="com.woniu.domain.Loantime">
    <!--
      WARNING - @mbggenerated
      This element is automatically generated by MyBatis Generator, do not modify.
      This element was generated on Mon Aug 19 19:11:51 CST 2019.
    -->
    update loantime
    set loantime = #{loantime,jdbcType=INTEGER}
    where loantimeid = #{loantimeid,jdbcType=INTEGER}
  </update>
</mapper>